[
  {
    "key": "apple",
    "value": "Apple",
    "items": [
      "iphone_15pro_max",
      "iphone_15pro",
      "iphone_15",
      "iphone_14pro_max",
      "iphone_14pro",
      "iphone_14plus",
      "iphone_14",
      "iphone_se_2022",
      "iphone_13pro_max",
      "iphone_13pro",
      "iphone_13",
      "iphone_13mini",
      "iphone_12pro_max",
      "iphone_12pro",
      "iphone_12",
      "iphone_12mini",
      "iphone_se_2020",
      "iphone_11pro_max",
      "iphone_11pro",
      "iphone_11",
      "iphone_xr",
      "iphone_xs_max",
      "iphone_x"
    ]
  },
  {
    "key": "xiaomi",
    "value": "Xiaomi",
    "items": [
      "xiaomi_13pro",
      "xiaomi_13",
      "xiaomi_12pro_max",
      "xiaomi_12pro",
      "xiaomi_12",
      "xiaomi_11t",
      "xiaomi_11",
      "xiaomi_redmi_note_12s",
      "xiaomi_redmi_note_12",
      "xiaomi_redmi_12",
      "xiaomi_redmi_10"
    ]
  },
  {
    "key": "samsung",
    "value": "Samsung",
    "items": [
      "samsung_s23ultra",
      "samsung_s23",
      "samsung_s22ultra",
      "samsung_s21ultra",
      "samsung_s21",
      "samsung_s20plus",
      "samsung_s20",
      "samsung_a53",
      "samsung_a52_s",
      "samsung_a52",
      "samsung_a34",
      "samsung_a33",
      "samsung_fe20"
    ]
  },
  {
    "key": "motorola",
    "value": "Motorola",
    "items": [
      "motorola_edge20",
      "motorola_edge40"
    ]
  }
]